mcp_diagram/__init__.py
mcp_diagram/format_extensions.py
iflow_mcp_angrysky56_mcp_diagram_server-0.1.0.dist-info/METADATA
iflow_mcp_angrysky56_mcp_diagram_server-0.1.0.dist-info/WHEEL
iflow_mcp_angrysky56_mcp_diagram_server-0.1.0.dist-info/entry_points.txt
iflow_mcp_angrysky56_mcp_diagram_server-0.1.0.dist-info/licenses/LICENSE
iflow_mcp_angrysky56_mcp_diagram_server-0.1.0.dist-info/RECORD
