Metadata-Version: 2.4
Name: iflow-mcp_angrysky56_mcp-diagram-server
Version: 0.1.0
Summary: MCP server for creating and manipulating Mermaid diagrams and charts
Project-URL: Documentation, https://github.com/ai-workspace/mcp-diagram-server#readme
Project-URL: Issues, https://github.com/ai-workspace/mcp-diagram-server/issues
Project-URL: Source, https://github.com/ai-workspace/mcp-diagram-server
Author-email: AI Workspace <workspace@example.com>
License-Expression: MIT
License-File: LICENSE
Keywords: diagrams,flowchart,mcp,mermaid,mindmap,visualization
Classifier: Development Status :: 4 - Beta
Classifier: Programming Language :: Python
Classifier: Programming Language :: Python :: 3.10
Classifier: Programming Language :: Python :: 3.11
Classifier: Programming Language :: Python :: 3.12
Requires-Python: >=3.10
Requires-Dist: aiofiles>=23.0.0
Requires-Dist: mcp[cli]>=1.2.0
Requires-Dist: pydantic>=2.0.0
Provides-Extra: advanced
Requires-Dist: cairosvg>=2.7.0; extra == 'advanced'
Requires-Dist: jinja2>=3.1.0; extra == 'advanced'
Requires-Dist: pillow>=10.0.0; extra == 'advanced'
Requires-Dist: playwright>=1.40.0; extra == 'advanced'
Requires-Dist: pyyaml>=6.0.0; extra == 'advanced'
Requires-Dist: watchdog>=3.0.0; extra == 'advanced'
Provides-Extra: dev
Requires-Dist: black>=23.0.0; extra == 'dev'
Requires-Dist: mypy>=1.0.0; extra == 'dev'
Requires-Dist: pytest-asyncio>=0.21.0; extra == 'dev'
Requires-Dist: pytest>=7.0.0; extra == 'dev'
Requires-Dist: ruff>=0.1.0; extra == 'dev'
